[
  {
    "ContainingType": "ApiWeb.Controllers.HangfireController",
    "Method": "DispararJob",
    "RelativePath": "api/Hangfire/disparar-job",
    "HttpMethod": "POST",
    "IsController": true,
    "Order": 0,
    "Parameters": [],
    "ReturnTypes": []
  },
  {
    "ContainingType": "ApiWeb.Controllers.LembreteController",
    "Method": "GetLembretes",
    "RelativePath": "api/v1/lembretes",
    "HttpMethod": "GET",
    "IsController": true,
    "Order": 0,
    "Parameters": [],
    "ReturnTypes": []
  },
  {
    "ContainingType": "ApiWeb.Controllers.LembreteController",
    "Method": "AddLembrete",
    "RelativePath": "api/v1/lembretes",
    "HttpMethod": "POST",
    "IsController": true,
    "Order": 0,
    "Parameters": [
      {
        "Name": "lembrete",
        "Type": "ApiWeb.Models.Lembrete",
        "IsRequired": true
      }
    ],
    "ReturnTypes": []
  },
  {
    "ContainingType": "ApiWeb.Controllers.LembreteController",
    "Method": "GetLembreteById",
    "RelativePath": "api/v1/lembretes/{id}",
    "HttpMethod": "GET",
    "IsController": true,
    "Order": 0,
    "Parameters": [
      {
        "Name": "id",
        "Type": "System.Int32",
        "IsRequired": true
      }
    ],
    "ReturnTypes": []
  },
  {
    "ContainingType": "ApiWeb.Controllers.LembreteController",
    "Method": "UpdateLembrete",
    "RelativePath": "api/v1/lembretes/{id}",
    "HttpMethod": "PUT",
    "IsController": true,
    "Order": 0,
    "Parameters": [
      {
        "Name": "id",
        "Type": "System.Int32",
        "IsRequired": true
      },
      {
        "Name": "lembrete",
        "Type": "ApiWeb.Models.Lembrete",
        "IsRequired": true
      }
    ],
    "ReturnTypes": []
  },
  {
    "ContainingType": "ApiWeb.Controllers.LembreteController",
    "Method": "DeleteLembrete",
    "RelativePath": "api/v1/lembretes/{id}",
    "HttpMethod": "DELETE",
    "IsController": true,
    "Order": 0,
    "Parameters": [
      {
        "Name": "id",
        "Type": "System.Int32",
        "IsRequired": true
      }
    ],
    "ReturnTypes": []
  },
  {
    "ContainingType": "ApiWeb.Controllers.LembreteController",
    "Method": "GetAllLembretes",
    "RelativePath": "api/v1/lembretes/todos",
    "HttpMethod": "GET",
    "IsController": true,
    "Order": 0,
    "Parameters": [],
    "ReturnTypes": []
  },
  {
    "ContainingType": "ApiWeb.Controllers.AuthController",
    "Method": "Login",
    "RelativePath": "api/v1/login",
    "HttpMethod": "POST",
    "IsController": true,
    "Order": 0,
    "Parameters": [
      {
        "Name": "userDto",
        "Type": "ApiWeb.Models.UserDto",
        "IsRequired": true
      }
    ],
    "ReturnTypes": []
  }
]